cseveutils/__init__.py
cseveutils/logger.py
cseveutils/hello/__init__.py
cseveutils/hello/pipipi.py
cseveutils-0.0.6.dist-info/METADATA
cseveutils-0.0.6.dist-info/WHEEL
cseveutils-0.0.6.dist-info/top_level.txt
cseveutils-0.0.6.dist-info/RECORD
