Metadata-Version: 2.1
Name: cseveutils
Version: 0.0.6
Summary: A Python library for loading
Home-page: UNKNOWN
Author: csilveira
Author-email: <csilveira@atech.com.br>
License: UNKNOWN
Keywords: python,utils,eve
Platform: UNKNOWN
Classifier: Development Status :: 1 - Planning
Classifier: Intended Audience :: Developers
Classifier: Programming Language :: Python :: 3
Classifier: Operating System :: Unix
Classifier: Operating System :: MacOS :: MacOS X
Classifier: Operating System :: Microsoft :: Windows
